MANIFEST.in
README.rst
setup.cfg
setup.py
pytest_simple_plugin/__init__.py
pytest_simple_plugin/plugin_module.py
pytest_simple_plugin.egg-info/PKG-INFO
pytest_simple_plugin.egg-info/SOURCES.txt
pytest_simple_plugin.egg-info/dependency_links.txt
pytest_simple_plugin.egg-info/entry_points.txt
pytest_simple_plugin.egg-info/requires.txt
pytest_simple_plugin.egg-info/top_level.txt